_meta/__init__.py
magentropy/__init__.py
magentropy/_calculations.py
magentropy/_classvars.py
magentropy/_grouping.py
magentropy/_pint_utils.py
magentropy/_plotting.py
magentropy/_smoothing.py
magentropy/_validation.py
magentropy/errors.py
magentropy/magentro.py
magentropy/typedefs.py
magentropy-0.1.6.dist-info/LICENSE
magentropy-0.1.6.dist-info/METADATA
magentropy-0.1.6.dist-info/WHEEL
magentropy-0.1.6.dist-info/top_level.txt
magentropy-0.1.6.dist-info/RECORD
