Metadata-Version: 2.1
Name: magentropy
Version: 0.1.6
Summary: Perform magnetoentropic mapping of magnetic materials based on DC magnetization data.
Author-email: Soren Bear <sorenbear@berkeley.edu>
License: MIT License
Project-URL: Download, https://pypi.org/project/magentropy/
Project-URL: Bug Tracker, https://github.com/sorenbear/magentropy/issues
Project-URL: Documentation, https://magentropy.readthedocs.io/en/stable/
Project-URL: Source Code, https://github.com/sorenbear/magentropy
Keywords: magentropy,magnetoentropy,magnetoentropic,magnetocaloric,magnetization,materials
Classifier: Development Status :: 4 - Beta
Classifier: Intended Audience :: Science/Research
Classifier: License :: OSI Approved :: MIT License
Classifier: Programming Language :: Python
Classifier: Programming Language :: Python :: 3
Classifier: Programming Language :: Python :: 3.9
Classifier: Programming Language :: Python :: 3.10
Classifier: Programming Language :: Python :: 3.11
Classifier: Topic :: Scientific/Engineering
Requires-Python: >=3.9
License-File: LICENSE
Requires-Dist: cycler >=0.11.0
Requires-Dist: matplotlib >=3.5.1
Requires-Dist: numba >=0.55.1
Requires-Dist: numpy >=1.21.5
Requires-Dist: pandas <2.0,>=1.4.3
Requires-Dist: pint >=0.19.2
Requires-Dist: pint-pandas >=0.2
Requires-Dist: scipy >=1.7.3
Provides-Extra: dev
Requires-Dist: build >=0.8.0 ; extra == 'dev'
Requires-Dist: furo >=2022.6.21 ; extra == 'dev'
Requires-Dist: ipykernel >=6.9.1 ; extra == 'dev'
Requires-Dist: myst-nb >=0.16.0 ; extra == 'dev'
Requires-Dist: myst-parser >=0.18.0 ; extra == 'dev'
Requires-Dist: numpydoc >=1.4.0 ; extra == 'dev'
Requires-Dist: pandoc >=2.2 ; extra == 'dev'
Requires-Dist: pylint >=2.12.2 ; extra == 'dev'
Requires-Dist: pytest >=7.1.2 ; extra == 'dev'
Requires-Dist: sphinx >=5.0.2 ; extra == 'dev'
Requires-Dist: sphinx-autobuild >=2021.3.14 ; extra == 'dev'
Requires-Dist: sphinx-copybutton >=0.5.0 ; extra == 'dev'
Requires-Dist: sphinxext-opengraph >=0.6.3 ; extra == 'dev'
Requires-Dist: twine >=4.0.1 ; extra == 'dev'
